LICENSE
README.md
setup.py
competitivepython/__init__.py
competitivepython.egg-info/PKG-INFO
competitivepython.egg-info/SOURCES.txt
competitivepython.egg-info/dependency_links.txt
competitivepython.egg-info/top_level.txt
competitivepython/graphs/__init__.py
competitivepython/graphs/bfs.py
competitivepython/graphs/dfs.py
competitivepython/graphs/dijkstra_shortest_path.py
competitivepython/searches/KMP_pattern_search.py
competitivepython/searches/__init__.py
competitivepython/searches/binarysearch.py
competitivepython/searches/linearsearch.py
competitivepython/sorting/__init__.py
competitivepython/sorting/bubblesort.py
competitivepython/sorting/bucketsort.py
competitivepython/sorting/heapsort.py
competitivepython/sorting/insertionsort.py
competitivepython/sorting/mergesort.py
competitivepython/sorting/quicksort.py
competitivepython/sorting/radixsort.py
competitivepython/sorting/selectionsort.py
competitivepython/sorting/shellsort.py
competitivepython/sorting/timsort.py
competitivepython/trees/__init__.py
competitivepython/trees/binary_search_tree.py