Metadata-Version: 2.1
Name: competitivepython
Version: 0.1.0
Summary: A collection of algorithms for competitive programming
Home-page: https://github.com/Shikha-code36/Competitive-Python
Author: Shikha Pandey
Author-email: shikha.py36@gmail.com
License: MIT
Keywords: competitive programming algorithm,python,data-structures,algorithms,searching-algorithm,sorting-algorithm,graphs,binary-search tree
Platform: UNKNOWN
Classifier: Development Status :: 3 - Alpha
Classifier: Intended Audience :: Developers
Classifier: Topic :: Software Development :: Libraries
Classifier: License :: OSI Approved :: MIT License
Classifier: Programming Language :: Python :: 3
Classifier: Programming Language :: Python :: 3.5
Classifier: Programming Language :: Python :: 3.6
Classifier: Programming Language :: Python :: 3.7
Classifier: Programming Language :: Python :: 3.8
Classifier: Programming Language :: Python :: 3.9
License-File: LICENSE
